{
	"info": {
		"_postman_id": "fdf8e11f-a389-452e-8cc4-3ec06a74bcf0",
		"name": "endpoints api",
		"schema": "https://schema.getpostman.com/json/collection/v2.1.0/collection.json",
		"_exporter_id": "24444547",
		"_collection_link": "https://www.postman.com/spacecraft-engineer-28699152/workspace/api-enerclic/collection/24444547-fdf8e11f-a389-452e-8cc4-3ec06a74bcf0?action=share&creator=24444547&source=collection_link"
	},
	"item": [
		{
			"name": "createUser",
			"request": {
				"method": "POST",
				"header": [],
				"body": {
					"mode": "raw",
					"raw": "{\r\n    \"nombre\":\"alejandro\",\r\n    \"email\":\"alejandro@example.com\",\r\n    \"password\":\"PruebaApi\"\r\n}",
					"options": {
						"raw": {
							"language": "json"
						}
					}
				},
				"url": {
					"raw": "http://localhost:3000/api/user/createUser",
					"protocol": "http",
					"host": [
						"localhost"
					],
					"port": "3000",
					"path": [
						"api",
						"user",
						"createUser"
					]
				}
			},
			"response": []
		},
		{
			"name": "login",
			"request": {
				"method": "POST",
				"header": [],
				"body": {
					"mode": "raw",
					"raw": "{\r\n    \"email\":\"alejandro@example.com\",\r\n    \"password\":\"PruebaApi\"\r\n}",
					"options": {
						"raw": {
							"language": "json"
						}
					}
				},
				"url": {
					"raw": "http://localhost:3000/api/user/login",
					"protocol": "http",
					"host": [
						"localhost"
					],
					"port": "3000",
					"path": [
						"api",
						"user",
						"login"
					]
				}
			},
			"response": []
		},
		{
			"name": "getData",
			"protocolProfileBehavior": {
				"disableBodyPruning": true
			},
			"request": {
				"auth": {
					"type": "jwt",
					"jwt": [
						{
							"key": "addTokenTo",
							"value": "header",
							"type": "string"
						},
						{
							"key": "secret",
							"value": "12345",
							"type": "string"
						},
						{
							"key": "algorithm",
							"value": "HS256",
							"type": "string"
						},
						{
							"key": "isSecretBase64Encoded",
							"value": false,
							"type": "boolean"
						},
						{
							"key": "payload",
							"value": "{}",
							"type": "string"
						},
						{
							"key": "headerPrefix",
							"value": "Bearer",
							"type": "string"
						},
						{
							"key": "queryParamKey",
							"value": "token",
							"type": "string"
						},
						{
							"key": "header",
							"value": "{}",
							"type": "string"
						}
					]
				},
				"method": "GET",
				"header": [],
				"body": {
					"mode": "raw",
					"raw": ""
				},
				"url": {
					"raw": "http://localhost:3000/api/device/getData",
					"protocol": "http",
					"host": [
						"localhost"
					],
					"port": "3000",
					"path": [
						"api",
						"device",
						"getData"
					]
				}
			},
			"response": []
		}
	]
}